{"cameraMode":{"drawMode":0,"name":"Shaded","section":"Shading Mode"},"sceneLighting":true,"audioPlay":false,"sceneViewState":{"m_AlwaysRefresh":false,"showFog":true,"showSkybox":true,"showFlares":true,"showImageEffects":true,"showParticleSystems":true,"showVisualEffectGraphs":true,"m_FxEnabled":true},"in2DMode":false,"pivot":{"x":11.876760482788086,"y":-1.31785249710083,"z":10.527095794677735},"rotation":{"x":-0.09914691746234894,"y":-0.36777886748313906,"z":0.039413973689079288,"w":-0.9237982630729675},"size":10.0,"orthographic":false}